starlark/__init__.py
starlark/__init__.pyi
starlark/py.typed
starlark/starlark.cp312-win_amd64.pyd
starlark_pyo3-2025.2.3.dist-info/METADATA
starlark_pyo3-2025.2.3.dist-info/WHEEL
starlark_pyo3-2025.2.3.dist-info/licenses/LICENSE
starlark_pyo3-2025.2.3.dist-info/RECORD
