Metadata-Version: 2.4
Name: starlark-pyo3
Version: 2025.2.3
Classifier: Programming Language :: Rust
Classifier: Programming Language :: Python :: Implementation :: CPython
Classifier: Programming Language :: Python :: Implementation :: PyPy
Requires-Dist: typing-extensions>=4.5
License-File: LICENSE
Summary: Wraps starlark-rust into Python
Home-Page: https://github.com/inducer/starlark-pyo3
Author-email: Andreas Kloeckner <inform@tiker.net>
Requires-Python: >=3.9
Project-URL: repository, https://github.com/inducer/starlark-pyo3
Project-URL: documentation, https://documen.tician.de/starlark-pyo3/
